cccpm/__init__.py
cccpm/cpm_analysis.py
cccpm/edge_selection.py
cccpm/fold.py
cccpm/logging.py
cccpm/models.py
cccpm/more_models.py
cccpm/reporting/__init__.py
cccpm/reporting/assets/CCCPM.png
cccpm/reporting/html_report.py
cccpm/reporting/plots/__init__.py
cccpm/reporting/plots/chord_v2.py
cccpm/reporting/plots/cpm_chord_plot.py
cccpm/reporting/plots/plots.py
cccpm/reporting/plots/utils.py
cccpm/reporting/reporting_utils.py
cccpm/results_manager.py
cccpm/scoring.py
cccpm/simulation/__init__.py
cccpm/simulation/simulate_multivariate.py
cccpm/simulation/simulate_sem.py
cccpm/simulation/simulate_simple.py
cccpm/utils.py
cccpm-0.2.1.dist-info/METADATA
cccpm-0.2.1.dist-info/WHEEL
cccpm-0.2.1.dist-info/RECORD
