Metadata-Version: 2.4
Name: cccpm
Version: 0.2.1
Summary: Confound-Corrected Connectome-based Predictive Modeling Python Package
License: MIT
Author: Nils Winter
Author-email: nils.r.winter@uni-muenster.de
Requires-Python: >=3.10,<4.0
Classifier: License :: OSI Approved :: MIT License
Classifier: Programming Language :: Python :: 3
Classifier: Programming Language :: Python :: 3.10
Classifier: Programming Language :: Python :: 3.11
Classifier: Programming Language :: Python :: 3.12
Classifier: Programming Language :: Python :: 3.13
Classifier: Programming Language :: Python :: 3.14
Requires-Dist: arakawa
Requires-Dist: bleach
Requires-Dist: netplotbrain
Requires-Dist: networkx
Requires-Dist: nilearn
Requires-Dist: numpy
Requires-Dist: pandas
Requires-Dist: plotly
Requires-Dist: pygam
Requires-Dist: scikit-image
Requires-Dist: scikit-learn (>=1.6)
Requires-Dist: tinycss2
Requires-Dist: tqdm
